[
  {
    "name": "(ဆင်ဖုံ)",
    "bus_ids": [
      "17",
      "19"
    ]
  },
  {
    "name": "(တူးချောင်း)",
    "bus_ids": [
      "23"
    ]
  },
  {
    "name": "(၅၀)ကွေ့",
    "bus_ids": [
      "12",
      "15"
    ]
  },
  {
    "name": "(၇/၈)လမ်းဆုံ",
    "bus_ids": [
      "12",
      "25"
    ]
  },
  {
    "name": "TBဆေးရုံ",
    "bus_ids": [
      "20"
    ]
  },
  {
    "name": "YTU",
    "bus_ids": [
      "15",
      "21",
      "39"
    ]
  },
  {
    "name": "ကမာကြည်လမ်း",
    "bus_ids": [
      "42"
    ]
  },
  {
    "name": "ကမ္ဘာအေးဘုရားလမ်း",
    "bus_ids": [
      "14",
      "28",
      "29",
      "30",
      "36",
      "38"
    ]
  },
  {
    "name": "ကမ်းနားလမ်း",
    "bus_ids": [
      "21",
      "23",
      "24",
      "26",
      "34",
      "35",
      "37",
      "39",
      "40",
      "56",
      "57",
      "57",
      "58"
    ]
  },
  {
    "name": "ကုက္ကိုင်း",
    "bus_ids": [
      "14",
      "38"
    ]
  },
  {
    "name": "ကုန်တိုက်",
    "bus_ids": [
      "7"
    ]
  },
  {
    "name": "ကုန်သည်လမ်း",
    "bus_ids": [
      "31",
      "56"
    ]
  },
  {
    "name": "ကော့မှူး",
    "bus_ids": [
      "49",
      "50"
    ]
  },
  {
    "name": "ကံဘဲ့",
    "bus_ids": [
      "47",
      "49",
      "50"
    ]
  },
  {
    "name": "ကံဘဲ့လမ်း",
    "bus_ids": [
      "12",
      "29"
    ]
  },
  {
    "name": "ကျန်စစ်သားလမ်း",
    "bus_ids": [
      "7",
      "29",
      "30",
      "53",
      "54"
    ]
  },
  {
    "name": "ကျန်စစ်သားလမ်း",
    "bus_ids": [
      "24"
    ]
  },
  {
    "name": "ကျိုက္ကဆံလမ်း",
    "bus_ids": [
      "3",
      "9",
      "18",
      "25",
      "27",
      "33"
    ]
  },
  {
    "name": "ကျိုက်ဝိုင်းဘုရားလမ်း",
    "bus_ids": [
      "6"
    ]
  },
  {
    "name": "ကျောက်ကုန်း",
    "bus_ids": [
      "60"
    ]
  },
  {
    "name": "ကျောက်တန်း",
    "bus_ids": [
      "33"
    ]
  },
  {
    "name": "ကျောက်တန်း(သန်လျင်လမ်း)",
    "bus_ids": [
      "33"
    ]
  },
  {
    "name": "ကျောက်တိုင်",
    "bus_ids": [
      "4",
      "5",
      "9",
      "9",
      "10",
      "32",
      "33"
    ]
  },
  {
    "name": "ကျောက်လမ်း",
    "bus_ids": [
      "16"
    ]
  },
  {
    "name": "ကျွန်းရွှေဝါလမ်း",
    "bus_ids": [
      "5"
    ]
  },
  {
    "name": "ကြက်ဘဲစျေး",
    "bus_ids": [
      "59"
    ]
  },
  {
    "name": "ကြက်ဘဲဈေး",
    "bus_ids": [
      "9",
      "18",
      "24",
      "25",
      "26"
    ]
  },
  {
    "name": "ကြည့်မြင့်တိုင်ကမ်းနားလမ်း",
    "bus_ids": [
      "59"
    ]
  },
  {
    "name": "ကြည့်မြင့်တိုင်",
    "bus_ids": [
      "30"
    ]
  },
  {
    "name": "ကြည့်မြင့်တိုင်ကမ်းနားလမ်း",
    "bus_ids": [
      "14"
    ]
  },
  {
    "name": "ကြိုးတံတား",
    "bus_ids": [
      "15"
    ]
  },
  {
    "name": "ကွန်ပြူတာတက္ကသိုလ်",
    "bus_ids": [
      "39"
    ]
  },
  {
    "name": "ကွမ်းခြံကုန်း",
    "bus_ids": [
      "49",
      "50"
    ]
  },
  {
    "name": "ကွေ့မ",
    "bus_ids": [
      "4"
    ]
  },
  {
    "name": "ခရမ်း",
    "bus_ids": [
      "34"
    ]
  },
  {
    "name": "ခရမ်း",
    "bus_ids": [
      "51"
    ]
  },
  {
    "name": "ခရေပင်လမ်းခွဲ",
    "bus_ids": [
      "11",
      "17",
      "35",
      "37",
      "42",
      "44"
    ]
  },
  {
    "name": "ခရေရိပ်မွန်",
    "bus_ids": [
      "18"
    ]
  },
  {
    "name": "ခရေရိပ်မွန်အိမ်ရာ",
    "bus_ids": [
      "11"
    ]
  },
  {
    "name": "ခရေရိပ်မွန်အိမ်ရာ",
    "bus_ids": [
      "32"
    ]
  },
  {
    "name": "ခေမာသီလမ်း",
    "bus_ids": [
      "2",
      "15"
    ]
  },
  {
    "name": "ချော်တွင်းကုန်း",
    "bus_ids": [
      "6",
      "10"
    ]
  },
  {
    "name": "ဂွတ္တလစ်ဈေး",
    "bus_ids": [
      "29"
    ]
  },
  {
    "name": "ဂွတ္တလစ်ဈေးကွေ့",
    "bus_ids": [
      "12"
    ]
  },
  {
    "name": "ငမိုးရိပ်တံတား",
    "bus_ids": [
      "25"
    ]
  },
  {
    "name": "စက်ဆန်းတံတား",
    "bus_ids": [
      "5"
    ]
  },
  {
    "name": "စက်မှု(၁)လမ်း",
    "bus_ids": [
      "14",
      "38"
    ]
  },
  {
    "name": "စက်မှုဇုန်",
    "bus_ids": [
      "7"
    ]
  },
  {
    "name": "စည်ပင်လမ်း",
    "bus_ids": [
      "3",
      "6"
    ]
  },
  {
    "name": "စလင်းကွင်း",
    "bus_ids": [
      "22"
    ]
  },
  {
    "name": "စိတ်ကျန်းမာရေးဆေးရုံ",
    "bus_ids": [
      "27"
    ]
  },
  {
    "name": "စီအိုတီ",
    "bus_ids": [
      "1"
    ]
  },
  {
    "name": "စော်ဘွားကြီးကုန်း",
    "bus_ids": [
      "6",
      "11",
      "37",
      "41"
    ]
  },
  {
    "name": "စံပြ",
    "bus_ids": [
      "21",
      "37",
      "39"
    ]
  },
  {
    "name": "စံပြငါးဈေး",
    "bus_ids": [
      "19",
      "20",
      "23",
      "40"
    ]
  },
  {
    "name": "စံပြဈေး",
    "bus_ids": [
      "1",
      "1",
      "3",
      "6",
      "7",
      "24"
    ]
  },
  {
    "name": "ဆင်မလိုက်",
    "bus_ids": [
      "14",
      "19",
      "20",
      "23",
      "38",
      "40"
    ]
  },
  {
    "name": "ဆူးလေ",
    "bus_ids": [
      "4",
      "7",
      "12",
      "29",
      "36",
      "61"
    ]
  },
  {
    "name": "ဆူးလေမြို့တော်ခန်းမ",
    "bus_ids": [
      "28"
    ]
  },
  {
    "name": "ဆေးတက္ကသိုလ်(၂)",
    "bus_ids": [
      "2"
    ]
  },
  {
    "name": "ဇင်ဂမလမ်း",
    "bus_ids": [
      "10"
    ]
  },
  {
    "name": "ဇရပ်ကွင်း(တာဆုံ)",
    "bus_ids": [
      "1"
    ]
  },
  {
    "name": "ဇဝန",
    "bus_ids": [
      "1",
      "7",
      "10",
      "18",
      "24",
      "32"
    ]
  },
  {
    "name": "ဇီဝကလမ်း",
    "bus_ids": [
      "11"
    ]
  },
  {
    "name": "ညောင်တန်း",
    "bus_ids": [
      "5"
    ]
  },
  {
    "name": "ညောင်တုန်းလမ်း",
    "bus_ids": [
      "53",
      "54"
    ]
  },
  {
    "name": "ညောင်ပင်",
    "bus_ids": [
      "30"
    ]
  },
  {
    "name": "တက္ကသိုလ်ရိပ်သာလမ်း",
    "bus_ids": [
      "14",
      "38"
    ]
  },
  {
    "name": "တညင်းကုန်း",
    "bus_ids": [
      "21",
      "39",
      "44"
    ]
  },
  {
    "name": "တညင်းကုန်းလမ်းဆုံ",
    "bus_ids": [
      "17",
      "40",
      "42"
    ]
  },
  {
    "name": "တပင်ရွှေထီးလမ်း",
    "bus_ids": [
      "24"
    ]
  },
  {
    "name": "တရုတ်ကုန်း",
    "bus_ids": [
      "1"
    ]
  },
  {
    "name": "တာဆုံ",
    "bus_ids": [
      "1",
      "43",
      "44"
    ]
  },
  {
    "name": "တာမွေ(ဗလီ)",
    "bus_ids": [
      "7",
      "25"
    ]
  },
  {
    "name": "တာမွေလမ်း",
    "bus_ids": [
      "20",
      "27"
    ]
  },
  {
    "name": "တာမွေအဝိုင်း",
    "bus_ids": [
      "3",
      "12",
      "14",
      "20",
      "26",
      "27",
      "29",
      "59"
    ]
  },
  {
    "name": "တိုက်ကြီး",
    "bus_ids": [
      "55"
    ]
  },
  {
    "name": "တိုင်းရင်းသား နည်းပညာတက္ကသိုလ်",
    "bus_ids": [
      "9"
    ]
  },
  {
    "name": "တိုင်းရင်းသားကျေးရွာ",
    "bus_ids": [
      "4",
      "5"
    ]
  },
  {
    "name": "တိုင်းရင်းသားကျေးရွာ",
    "bus_ids": [
      "10"
    ]
  },
  {
    "name": "တောင်ဒဂုံ",
    "bus_ids": [
      "60"
    ]
  },
  {
    "name": "တောင်ဒဂုံ(၇၀/၇၂)ရပ်ကွက်",
    "bus_ids": [
      "7"
    ]
  },
  {
    "name": "တောင်မြောက်လမ်းဆုံ",
    "bus_ids": [
      "1",
      "2",
      "3",
      "6",
      "7",
      "24",
      "25",
      "46",
      "60"
    ]
  },
  {
    "name": "တောင်ဥက္ကလာဘုရား",
    "bus_ids": [
      "38"
    ]
  },
  {
    "name": "တွံတေး",
    "bus_ids": [
      "47",
      "48"
    ]
  },
  {
    "name": "တွံတေးကြိုးတံတား",
    "bus_ids": [
      "47",
      "49"
    ]
  },
  {
    "name": "တွံတေးမြို့",
    "bus_ids": [
      "47"
    ]
  },
  {
    "name": "ထန်းခြောက်ပင်",
    "bus_ids": [
      "40",
      "42"
    ]
  },
  {
    "name": "ထန်းတစ်ပင်",
    "bus_ids": [
      "52"
    ]
  },
  {
    "name": "ထောက်ကြန့်",
    "bus_ids": [
      "41"
    ]
  },
  {
    "name": "ထောက်ကြန့်",
    "bus_ids": [
      "44",
      "55"
    ]
  },
  {
    "name": "ထောက်ကြန့်",
    "bus_ids": [
      "35",
      "36",
      "37"
    ]
  },
  {
    "name": "ဒဂုံတက္ကသိုလ်",
    "bus_ids": [
      "10",
      "27"
    ]
  },
  {
    "name": "ဒဂုံတက္ကသိုလ်",
    "bus_ids": [
      "25",
      "26",
      "28",
      "29",
      "30"
    ]
  },
  {
    "name": "ဒဂုံပန်းခြံကွေ့",
    "bus_ids": [
      "8"
    ]
  },
  {
    "name": "ဒဂုံမြောက်(ဘုရင့်နောင်လမ်းဆုံ)",
    "bus_ids": [
      "14"
    ]
  },
  {
    "name": "ဒဂုံဧရာအဝေးပြေးဝင်း",
    "bus_ids": [
      "16",
      "20",
      "61"
    ]
  },
  {
    "name": "ဒရယ်ဖို",
    "bus_ids": [
      "1"
    ]
  },
  {
    "name": "ဒလ",
    "bus_ids": [
      "48",
      "50"
    ]
  },
  {
    "name": "ဒါးပိန်",
    "bus_ids": [
      "46"
    ]
  },
  {
    "name": "ဒေါပုံ",
    "bus_ids": [
      "9",
      "33"
    ]
  },
  {
    "name": "ဓမ္မစေတီလမ်း",
    "bus_ids": [
      "11",
      "59"
    ]
  },
  {
    "name": "နတ်မောက်လမ်း",
    "bus_ids": [
      "8"
    ]
  },
  {
    "name": "နန္ဒဝန်ဈေး",
    "bus_ids": [
      "12"
    ]
  },
  {
    "name": "နဝဒေး",
    "bus_ids": [
      "6",
      "10",
      "15",
      "16",
      "19",
      "28",
      "36"
    ]
  },
  {
    "name": "နွယ်ခွေ",
    "bus_ids": [
      "35",
      "36"
    ]
  },
  {
    "name": "နှင်းဆီကုန်းလမ်း",
    "bus_ids": [
      "59"
    ]
  },
  {
    "name": "ပင်လုံလမ်း",
    "bus_ids": [
      "14",
      "26",
      "29"
    ]
  },
  {
    "name": "ပါရမီ",
    "bus_ids": [
      "30"
    ]
  },
  {
    "name": "ပါရမီလမ်း",
    "bus_ids": [
      "10",
      "12",
      "18",
      "32"
    ]
  },
  {
    "name": "ပုဇွန်တောင်ဈေး",
    "bus_ids": [
      "24",
      "26"
    ]
  },
  {
    "name": "ပုလဲမြို့သစ်",
    "bus_ids": [
      "36"
    ]
  },
  {
    "name": "ပုလဲလမ်း",
    "bus_ids": [
      "40"
    ]
  },
  {
    "name": "ပုသိမ်လမ်း",
    "bus_ids": [
      "16",
      "23",
      "54"
    ]
  },
  {
    "name": "ပေါက်ကုန်း",
    "bus_ids": [
      "1"
    ]
  },
  {
    "name": "ပေါက်ကုန်းအဝိုင်း",
    "bus_ids": [
      "21",
      "22"
    ]
  },
  {
    "name": "ပေါက်တန်းအဝိုင်း",
    "bus_ids": [
      "17"
    ]
  },
  {
    "name": "ပေါက်တောဝ",
    "bus_ids": [
      "15",
      "22",
      "40"
    ]
  },
  {
    "name": "ပဲခူး",
    "bus_ids": [
      "51"
    ]
  },
  {
    "name": "ပဲခူးမြစ်လမ်း",
    "bus_ids": [
      "3",
      "4",
      "5"
    ]
  },
  {
    "name": "ပြည်တော်သာ",
    "bus_ids": [
      "21",
      "40"
    ]
  },
  {
    "name": "ပြည်တော်သာ(အောက်လမ်း)",
    "bus_ids": [
      "39"
    ]
  },
  {
    "name": "ပြည်ထောင်စုလမ်း",
    "bus_ids": [
      "2",
      "2",
      "7",
      "15",
      "24",
      "25",
      "26",
      "27",
      "29",
      "30"
    ]
  },
  {
    "name": "ပြည်ထောင်စုလမ်းဆုံ",
    "bus_ids": [
      "60"
    ]
  },
  {
    "name": "ပြည်ထောင်စုလမ်းမကြီး",
    "bus_ids": [
      "60"
    ]
  },
  {
    "name": "ပြည်လမ်း",
    "bus_ids": [
      "6",
      "35",
      "37",
      "41",
      "43"
    ]
  },
  {
    "name": "ဖောင်ကြီး",
    "bus_ids": [
      "45"
    ]
  },
  {
    "name": "ဖောင်ကြီးလမ်း",
    "bus_ids": [
      "45"
    ]
  },
  {
    "name": "ဗညားဒလလမ်း",
    "bus_ids": [
      "3",
      "20",
      "27",
      "33"
    ]
  },
  {
    "name": "ဗဟန်း(၃)လမ်း",
    "bus_ids": [
      "28",
      "36"
    ]
  },
  {
    "name": "ဗဟိုလမ်း",
    "bus_ids": [
      "11",
      "11",
      "22",
      "22"
    ]
  },
  {
    "name": "ဗဟိုအမျိုးသမီးဆေးရုံ",
    "bus_ids": [
      "22"
    ]
  },
  {
    "name": "ဗားကရာ",
    "bus_ids": [
      "22"
    ]
  },
  {
    "name": "ဗားကရာလမ်း",
    "bus_ids": [
      "11",
      "20",
      "59"
    ]
  },
  {
    "name": "ဗိုလ်ချုပ်နေဝင်းလမ်း",
    "bus_ids": [
      "32"
    ]
  },
  {
    "name": "ဗိုလ်ချုပ်အောင်ဆန်းလမ်း",
    "bus_ids": [
      "5",
      "56"
    ]
  },
  {
    "name": "ဗိုလ်တထောင်",
    "bus_ids": [
      "57"
    ]
  },
  {
    "name": "ဗိုလ်တထောင်ဈေးလမ်း",
    "bus_ids": [
      "31",
      "31"
    ]
  },
  {
    "name": "ဗိုလ်တထောင်ဘုရား",
    "bus_ids": [
      "58"
    ]
  },
  {
    "name": "ဗိုလ်တထောင်ဘုရား(ကမ်းနားလမ်း)",
    "bus_ids": [
      "58"
    ]
  },
  {
    "name": "ဗိုလ်တထောင်ဘုရားလမ်း",
    "bus_ids": [
      "5",
      "24",
      "26",
      "31",
      "34",
      "56",
      "58"
    ]
  },
  {
    "name": "ဗိုလ်မှူးဗထူးလမ်း",
    "bus_ids": [
      "2",
      "10",
      "27",
      "28"
    ]
  },
  {
    "name": "ဗိုလ်အောင်ကျော်လမ်း",
    "bus_ids": [
      "53",
      "54",
      "54"
    ]
  },
  {
    "name": "ဘီအိုစီ",
    "bus_ids": [
      "15",
      "39"
    ]
  },
  {
    "name": "ဘီအိုစီအဝိုင်း",
    "bus_ids": [
      "20",
      "23",
      "61"
    ]
  },
  {
    "name": "ဘုန်းကြီးကျောင်းကွေ့",
    "bus_ids": [
      "7"
    ]
  },
  {
    "name": "ဘုန်းကြီးလမ်း",
    "bus_ids": [
      "18",
      "32",
      "35",
      "37",
      "39",
      "42"
    ]
  },
  {
    "name": "ဘုရင့်နောင်",
    "bus_ids": [
      "40"
    ]
  },
  {
    "name": "ဘုရင့်နောင်တံတား",
    "bus_ids": [
      "16",
      "20",
      "23"
    ]
  },
  {
    "name": "ဘုရင့်နောင်လမ်း",
    "bus_ids": [
      "14",
      "15",
      "19",
      "20",
      "23",
      "38",
      "42",
      "61"
    ]
  },
  {
    "name": "ဘုရင့်နောင်လမ်းဆုံ",
    "bus_ids": [
      "15",
      "19",
      "61"
    ]
  },
  {
    "name": "ဘုရင့်နောင်လမ်းမကြီး",
    "bus_ids": [
      "40"
    ]
  },
  {
    "name": "ဘုရားငုတ်တို",
    "bus_ids": [
      "47",
      "48",
      "49",
      "50"
    ]
  },
  {
    "name": "ဘုရားလမ်း",
    "bus_ids": [
      "57"
    ]
  },
  {
    "name": "ဘုရားလမ်းဆုံ",
    "bus_ids": [
      "32"
    ]
  },
  {
    "name": "ဘေလီ",
    "bus_ids": [
      "6",
      "12",
      "14",
      "18",
      "26",
      "27",
      "29",
      "30",
      "32"
    ]
  },
  {
    "name": "ဘေလီ",
    "bus_ids": [
      "38"
    ]
  },
  {
    "name": "မင်းကုန်း",
    "bus_ids": [
      "45"
    ]
  },
  {
    "name": "မင်းကြီးလမ်း",
    "bus_ids": [
      "21"
    ]
  },
  {
    "name": "မင်းဓမ္မလမ်း",
    "bus_ids": [
      "6"
    ]
  },
  {
    "name": "မင်းနန္ဒာလမ်း",
    "bus_ids": [
      "4",
      "5",
      "8",
      "9",
      "10",
      "33"
    ]
  },
  {
    "name": "မင်းရဲကျော်စွာလမ်း",
    "bus_ids": [
      "25",
      "26",
      "27",
      "27",
      "29",
      "30"
    ]
  },
  {
    "name": "မင်္ဂလာဈေး",
    "bus_ids": [
      "3",
      "7",
      "8",
      "25",
      "27",
      "33"
    ]
  },
  {
    "name": "မဝတလမ်းဆုံ",
    "bus_ids": [
      "12"
    ]
  },
  {
    "name": "မဟာဗန္ဓုလတံတား",
    "bus_ids": [
      "4",
      "31",
      "34"
    ]
  },
  {
    "name": "မဟာဗန္ဓုလတံတားအောက်",
    "bus_ids": [
      "24",
      "26"
    ]
  },
  {
    "name": "မဟာဗန္ဓုလလမ်း",
    "bus_ids": [
      "4",
      "7",
      "21",
      "34",
      "35",
      "37",
      "39",
      "42",
      "57"
    ]
  },
  {
    "name": "မိုးကောင်းလမ်း",
    "bus_ids": [
      "12",
      "14",
      "26",
      "27",
      "38"
    ]
  },
  {
    "name": "မီးခွက်စျေး",
    "bus_ids": [
      "61"
    ]
  },
  {
    "name": "မီးခွက်ဈေး",
    "bus_ids": [
      "22",
      "52"
    ]
  },
  {
    "name": "မောင်းမကန်လမ်း",
    "bus_ids": [
      "2",
      "3",
      "6"
    ]
  },
  {
    "name": "မော်တင်",
    "bus_ids": [
      "21",
      "35",
      "37",
      "39"
    ]
  },
  {
    "name": "မြင်တော်သာလမ်း",
    "bus_ids": [
      "8",
      "34"
    ]
  },
  {
    "name": "မြင်သာ(ကညန)",
    "bus_ids": [
      "1"
    ]
  },
  {
    "name": "မြန်မာ့ဂုဏ်ရည်လမ်း",
    "bus_ids": [
      "20"
    ]
  },
  {
    "name": "မြရာကုန်းလမ်း",
    "bus_ids": [
      "20"
    ]
  },
  {
    "name": "မြေနီကုန်း",
    "bus_ids": [
      "11",
      "20",
      "21",
      "35",
      "37",
      "39",
      "61"
    ]
  },
  {
    "name": "မြောက်ဥက္ကလာပဆေးရုံ",
    "bus_ids": [
      "2"
    ]
  },
  {
    "name": "မြောက်ဥက္ကလာပအဝိုင်း",
    "bus_ids": [
      "2",
      "10",
      "15",
      "16",
      "19",
      "28",
      "32",
      "36"
    ]
  },
  {
    "name": "မြောင်းတကာ",
    "bus_ids": [
      "55"
    ]
  },
  {
    "name": "မှော်ဘီ",
    "bus_ids": [
      "55"
    ]
  },
  {
    "name": "မှော်ဘီဈေးရှေ့",
    "bus_ids": [
      "43"
    ]
  },
  {
    "name": "မှော်ဘီနည်းပညာတက္ကသိုလ်",
    "bus_ids": [
      "55"
    ]
  },
  {
    "name": "ယမုံနာလမ်း",
    "bus_ids": [
      "8",
      "31"
    ]
  },
  {
    "name": "ယုဇန(ခိုင်ရွှေဝါလမ်း)",
    "bus_ids": [
      "2"
    ]
  },
  {
    "name": "ယုဇနပလာဇာ",
    "bus_ids": [
      "3",
      "9",
      "20",
      "25",
      "27",
      "33"
    ]
  },
  {
    "name": "ယုဇနဥယျာဉ်",
    "bus_ids": [
      "5"
    ]
  },
  {
    "name": "ယုဇနဥယျာဉ်မြို့တော်",
    "bus_ids": [
      "3",
      "4"
    ]
  },
  {
    "name": "ရတနာပုံလမ်း",
    "bus_ids": [
      "7"
    ]
  },
  {
    "name": "ရတနာလမ်း(ဒဂုံဆိပ်ကမ်း)",
    "bus_ids": [
      "4",
      "5"
    ]
  },
  {
    "name": "ရတနာလမ်း(သင်္ဃန်းကျွန်း)",
    "bus_ids": [
      "1",
      "14",
      "26",
      "27",
      "42",
      "60"
    ]
  },
  {
    "name": "ရန်ကင်းစင်တာ",
    "bus_ids": [
      "14"
    ]
  },
  {
    "name": "ရန်ကင်းလမ်း",
    "bus_ids": [
      "12",
      "14",
      "29",
      "38"
    ]
  },
  {
    "name": "ရန်ကုန်ညောင်တုန်းလမ်း",
    "bus_ids": [
      "52"
    ]
  },
  {
    "name": "ရန်ကုန်ပုသိမ်လမ်း",
    "bus_ids": [
      "52"
    ]
  },
  {
    "name": "ရန်ကုန်ပဲခူးလမ်း",
    "bus_ids": [
      "44"
    ]
  },
  {
    "name": "ရန်ကုန်ဘူတာကြီး",
    "bus_ids": [
      "12",
      "28",
      "29",
      "36",
      "61"
    ]
  },
  {
    "name": "ရန်ရှင်းလမ်း",
    "bus_ids": [
      "14",
      "38"
    ]
  },
  {
    "name": "ရာဇဓိရာဇ်လမ်း",
    "bus_ids": [
      "24",
      "26"
    ]
  },
  {
    "name": "ရာဇာသင်္ကြန်လမ်း",
    "bus_ids": [
      "15"
    ]
  },
  {
    "name": "ရိုးကြီး/ရိုးလေး",
    "bus_ids": [
      "22"
    ]
  },
  {
    "name": "ရိုးမရိပ်သာ",
    "bus_ids": [
      "5"
    ]
  },
  {
    "name": "ရေကြောင်းတက္ကသိုလ်",
    "bus_ids": [
      "32"
    ]
  },
  {
    "name": "ရဲမွန်",
    "bus_ids": [
      "1"
    ]
  },
  {
    "name": "ရွာမကျောင်းလမ်း",
    "bus_ids": [
      "11",
      "22"
    ]
  },
  {
    "name": "ရွာသာကြီး(စီးပွားရေးတက္ကသိုလ်)",
    "bus_ids": [
      "1",
      "46"
    ]
  },
  {
    "name": "ရွှေဂုံတိုင်",
    "bus_ids": [
      "12",
      "20",
      "29",
      "61"
    ]
  },
  {
    "name": "ရွှေဂုံတိုင်ဂုံးကျော်တံတား",
    "bus_ids": [
      "59"
    ]
  },
  {
    "name": "ရွှေဂုံတိုင်လမ်း",
    "bus_ids": [
      "12",
      "59"
    ]
  },
  {
    "name": "ရွှေဂုံလမ်း",
    "bus_ids": [
      "59"
    ]
  },
  {
    "name": "ရွှေတိဂုံဘုရားလမ်း",
    "bus_ids": [
      "8",
      "11"
    ]
  },
  {
    "name": "ရွှေပေါက်ကံ",
    "bus_ids": [
      "17",
      "19"
    ]
  },
  {
    "name": "ရွှေပေါက်ကံ(တောင်ငူလမ်း)",
    "bus_ids": [
      "16"
    ]
  },
  {
    "name": "ရွှေပြည်သာ(လိန်ကုန်း)",
    "bus_ids": [
      "39",
      "40",
      "42"
    ]
  },
  {
    "name": "ရွှေပြည်သာကွေ့",
    "bus_ids": [
      "42"
    ]
  },
  {
    "name": "ရွှေပြည်သာတံတား",
    "bus_ids": [
      "17",
      "21"
    ]
  },
  {
    "name": "ရွှေဗဟိုရ်",
    "bus_ids": [
      "9",
      "25"
    ]
  },
  {
    "name": "ရွှေရင်အေးလမ်း",
    "bus_ids": [
      "54",
      "54"
    ]
  },
  {
    "name": "ရွှေလင်ဗန်းလမ်းဆုံ",
    "bus_ids": [
      "53"
    ]
  },
  {
    "name": "ရွှေလင်ဗန်းလမ်းဆုံ",
    "bus_ids": [
      "53"
    ]
  },
  {
    "name": "ရွှေလီလမ်း",
    "bus_ids": [
      "5"
    ]
  },
  {
    "name": "ရှစ်မိုင်လမ်းဆုံ",
    "bus_ids": [
      "61"
    ]
  },
  {
    "name": "ရှုခင်းသာမြို့ပါတ်လမ်း",
    "bus_ids": [
      "10",
      "31",
      "42"
    ]
  },
  {
    "name": "လင့်လမ်း",
    "bus_ids": [
      "11",
      "20"
    ]
  },
  {
    "name": "လမ်းသစ်လမ်း",
    "bus_ids": [
      "41"
    ]
  },
  {
    "name": "လိန်ကုန်း",
    "bus_ids": [
      "43",
      "44"
    ]
  },
  {
    "name": "လေးထောင့်ကန်လမ်း",
    "bus_ids": [
      "3",
      "18",
      "24",
      "32"
    ]
  },
  {
    "name": "လှည်တန်းလမ်း",
    "bus_ids": [
      "41"
    ]
  },
  {
    "name": "လှည်းကူးဈေးရှေ့",
    "bus_ids": [
      "1",
      "45"
    ]
  },
  {
    "name": "လှည်းကူးဈေးရှေ့",
    "bus_ids": [
      "44"
    ]
  },
  {
    "name": "လှည်းတန်း",
    "bus_ids": [
      "21",
      "35",
      "37",
      "39",
      "61"
    ]
  },
  {
    "name": "လှည်းတန်းခိုင်ရွှေဝါ",
    "bus_ids": [
      "11",
      "22"
    ]
  },
  {
    "name": "လှည်းတန်းလမ်း",
    "bus_ids": [
      "14",
      "30",
      "38"
    ]
  },
  {
    "name": "လှိုင်သာယာ ဘီအိုစီ",
    "bus_ids": [
      "47",
      "49"
    ]
  },
  {
    "name": "လှော်ကားလမ်း",
    "bus_ids": [
      "2",
      "6",
      "7",
      "42",
      "43",
      "44"
    ]
  },
  {
    "name": "ဝေဇယန္တာလမ်း",
    "bus_ids": [
      "18",
      "32"
    ]
  },
  {
    "name": "သခင်မြပန်းခြံ",
    "bus_ids": [
      "14",
      "19",
      "22",
      "23",
      "30",
      "40",
      "41",
      "56",
      "57"
    ]
  },
  {
    "name": "သခင်မြပန်းခြံ",
    "bus_ids": [
      "56",
      "57"
    ]
  },
  {
    "name": "သခင်မြပန်းခြံလမ်း",
    "bus_ids": [
      "59"
    ]
  },
  {
    "name": "သင်္ဃန်းကျွန်း",
    "bus_ids": [
      "1"
    ]
  },
  {
    "name": "သင်္ဃန်းကျွန်းစံပြစျေး",
    "bus_ids": [
      "60"
    ]
  },
  {
    "name": "သင်္ဃန်းကျွန်းစံပြဈေး",
    "bus_ids": [
      "59"
    ]
  },
  {
    "name": "သစ္စာလမ်း",
    "bus_ids": [
      "12",
      "29",
      "38"
    ]
  },
  {
    "name": "သနပ်ပင်",
    "bus_ids": [
      "1",
      "51"
    ]
  },
  {
    "name": "သန်လျင်(မြို့မဈေး)",
    "bus_ids": [
      "32"
    ]
  },
  {
    "name": "သန်လျင်(အရှေ့ပိုင်းတက္ကသိုလ်)",
    "bus_ids": [
      "31"
    ]
  },
  {
    "name": "သန်လျင်ကျောက်တန်း လမ်း",
    "bus_ids": [
      "34"
    ]
  },
  {
    "name": "သန်လျင်ကျောက်တန်းလမ်း",
    "bus_ids": [
      "31"
    ]
  },
  {
    "name": "သန်လျင်အမှတ်(၁)တံတား",
    "bus_ids": [
      "31",
      "32",
      "33",
      "34"
    ]
  },
  {
    "name": "သမကုန်း",
    "bus_ids": [
      "16",
      "22"
    ]
  },
  {
    "name": "သမကုန်းအဝိုင်း",
    "bus_ids": [
      "17",
      "20",
      "23",
      "61"
    ]
  },
  {
    "name": "သမိန်ဗရမ်းလမ်း",
    "bus_ids": [
      "9",
      "18",
      "25",
      "26",
      "59"
    ]
  },
  {
    "name": "သမိုင်းလမ်းဆုံ",
    "bus_ids": [
      "15",
      "15",
      "19",
      "21",
      "39",
      "61"
    ]
  },
  {
    "name": "သာကေတ(အဝိုင်း)",
    "bus_ids": [
      "5",
      "8",
      "34"
    ]
  },
  {
    "name": "သာကေတတံတား",
    "bus_ids": [
      "8",
      "9"
    ]
  },
  {
    "name": "သာကေတအဝိုင်း",
    "bus_ids": [
      "4",
      "32",
      "33",
      "42"
    ]
  },
  {
    "name": "သာကေတဧရာဝဏ်",
    "bus_ids": [
      "60"
    ]
  },
  {
    "name": "သိမ်ဖြူ",
    "bus_ids": [
      "7",
      "20",
      "20"
    ]
  },
  {
    "name": "သိမ်ဖြူလမ်း",
    "bus_ids": [
      "34"
    ]
  },
  {
    "name": "သီရိမင်္ဂလာဈေးသစ်",
    "bus_ids": [
      "19",
      "20",
      "23",
      "38",
      "40"
    ]
  },
  {
    "name": "သုဓမ္မာလမ်း",
    "bus_ids": [
      "2",
      "8",
      "10",
      "15",
      "18",
      "19",
      "36",
      "42"
    ]
  },
  {
    "name": "သုမင်္ဂလာ",
    "bus_ids": [
      "1"
    ]
  },
  {
    "name": "သုမင်္ဂလာလမ်း",
    "bus_ids": [
      "10",
      "32"
    ]
  },
  {
    "name": "သုဝဏ္ဏတံတား",
    "bus_ids": [
      "9",
      "10",
      "24",
      "32"
    ]
  },
  {
    "name": "သုံးခွ",
    "bus_ids": [
      "34"
    ]
  },
  {
    "name": "သံလျင်တံတားချဉ်းကပ်လမ်း",
    "bus_ids": [
      "4",
      "42"
    ]
  },
  {
    "name": "သံသုမာ",
    "bus_ids": [
      "59"
    ]
  },
  {
    "name": "သံသုမာလမ်း",
    "bus_ids": [
      "6",
      "9",
      "14",
      "18",
      "18",
      "24",
      "25",
      "26",
      "27",
      "29",
      "32",
      "38",
      "42",
      "60"
    ]
  },
  {
    "name": "သွေးဆေးကန်လမ်း",
    "bus_ids": [
      "11"
    ]
  },
  {
    "name": "ဟံသာဝတီ",
    "bus_ids": [
      "22"
    ]
  },
  {
    "name": "ဟံသာဝတီလမ်း",
    "bus_ids": [
      "11"
    ]
  },
  {
    "name": "အင်းစိန်ပန်းခြံ",
    "bus_ids": [
      "11",
      "15",
      "21",
      "22",
      "41"
    ]
  },
  {
    "name": "အင်းတိုင်",
    "bus_ids": [
      "1"
    ]
  },
  {
    "name": "အင်းဝ အိမ်ရာ",
    "bus_ids": [
      "8"
    ]
  },
  {
    "name": "အထက်ကြည့်မြင့်တိုင်လမ်း",
    "bus_ids": [
      "22",
      "41"
    ]
  },
  {
    "name": "အထက်ကြည့်မြင့်တိုင်လမ်း",
    "bus_ids": [
      "11"
    ]
  },
  {
    "name": "အထက်ပုဇွန်တောင်လမ်း",
    "bus_ids": [
      "24",
      "26"
    ]
  },
  {
    "name": "အနောက်ကြို့ကုန်း",
    "bus_ids": [
      "22"
    ]
  },
  {
    "name": "အနောက်ပိုင်းဆေးရုံ",
    "bus_ids": [
      "22"
    ]
  },
  {
    "name": "အနောက်ပိုင်းတက္ကသိုလ်(ထန်းတပင်)",
    "bus_ids": [
      "21",
      "22"
    ]
  },
  {
    "name": "အနောက်ပိုင်းနည်းပညာတက္ကသိုလ်",
    "bus_ids": [
      "17",
      "23"
    ]
  },
  {
    "name": "အနောက်ပိုင်းနည်းပညာတက္ကသိုလ်",
    "bus_ids": [
      "61"
    ]
  },
  {
    "name": "အနောက်ရွှေဂုံတိုင်လမ်း",
    "bus_ids": [
      "11"
    ]
  },
  {
    "name": "အနော်ရထာလမ်း",
    "bus_ids": [
      "4",
      "5",
      "7",
      "31",
      "54",
      "58"
    ]
  },
  {
    "name": "အမှတ်(၂)လမ်း",
    "bus_ids": [
      "2",
      "46",
      "60"
    ]
  },
  {
    "name": "အမှတ်(၃)လမ်း",
    "bus_ids": [
      "36"
    ]
  },
  {
    "name": "အမှတ်(၃)လမ်းဆုံ",
    "bus_ids": [
      "18",
      "32",
      "35",
      "36",
      "42"
    ]
  },
  {
    "name": "အမှတ်(၃)လမ်းပုလဲမြို့သစ်",
    "bus_ids": [
      "35"
    ]
  },
  {
    "name": "အမှတ်(၄)လမ်း",
    "bus_ids": [
      "39",
      "43",
      "44"
    ]
  },
  {
    "name": "အရှေ့ပိုင်းတက္ကသိုလ်",
    "bus_ids": [
      "34"
    ]
  },
  {
    "name": "အရှေ့မြင်းပြိုင်ကွင်းလမ်း",
    "bus_ids": [
      "3",
      "18",
      "26",
      "27"
    ]
  },
  {
    "name": "အလုံလျှပ်စစ်ရုံး",
    "bus_ids": [
      "22"
    ]
  },
  {
    "name": "အသင်းတိုက်",
    "bus_ids": [
      "10",
      "18",
      "24"
    ]
  },
  {
    "name": "အာသောကလမ်း",
    "bus_ids": [
      "59"
    ]
  },
  {
    "name": "အောက်ကြည့်မြင့်တိုင်လမ်း",
    "bus_ids": [
      "41",
      "59"
    ]
  },
  {
    "name": "အောက်ထိပ်",
    "bus_ids": [
      "54"
    ]
  },
  {
    "name": "အောက်မင်္ဂလာဒုံလမ်း",
    "bus_ids": [
      "21"
    ]
  },
  {
    "name": "အောင်ဇေယျတံတား",
    "bus_ids": [
      "22",
      "61"
    ]
  },
  {
    "name": "အောင်ဇေယျလမ်း",
    "bus_ids": [
      "26",
      "60"
    ]
  },
  {
    "name": "အောင်မင်္ဂလာအဝေးပြေးဝင်း",
    "bus_ids": [
      "2",
      "17",
      "18"
    ]
  },
  {
    "name": "အောင်မြင့်မိုရ်",
    "bus_ids": [
      "6"
    ]
  },
  {
    "name": "ဥက္ကံ",
    "bus_ids": [
      "55"
    ]
  },
  {
    "name": "ဦးချစ်မောင်လမ်း",
    "bus_ids": [
      "14"
    ]
  },
  {
    "name": "ဦးထောင်ဘိုလမ်း",
    "bus_ids": [
      "8",
      "8",
      "11"
    ]
  },
  {
    "name": "ဦးဝိစာရလမ်း",
    "bus_ids": [
      "8",
      "11",
      "27"
    ]
  },
  {
    "name": "ဧရာဝဏ်လမ်း",
    "bus_ids": [
      "3",
      "4",
      "8",
      "9",
      "32"
    ]
  },
  {
    "name": "၁၀မိုင်ကုန်း",
    "bus_ids": [
      "6",
      "37"
    ]
  },
  {
    "name": "၁၃၃ရပ်ကွက်",
    "bus_ids": [
      "27"
    ]
  },
  {
    "name": "၁၄လမ်းဆုံ",
    "bus_ids": [
      "21",
      "40"
    ]
  },
  {
    "name": "၃ထောင်ကွေ့",
    "bus_ids": [
      "41"
    ]
  },
  {
    "name": "၄၆လမ်းဆုံ",
    "bus_ids": [
      "12"
    ]
  },
  {
    "name": "၅ကွေ့",
    "bus_ids": [
      "10"
    ]
  },
  {
    "name": "၆ကွေ့",
    "bus_ids": [
      "2",
      "16",
      "17",
      "18",
      "19"
    ]
  },
  {
    "name": "၇ဈေးလမ်း",
    "bus_ids": [
      "8"
    ]
  },
  {
    "name": "၈မိုင်လမ်းဆုံ",
    "bus_ids": [
      "6",
      "6",
      "15",
      "16",
      "19",
      "30",
      "35",
      "37"
    ]
  },
  {
    "name": "၈၆ဂိတ်",
    "bus_ids": [
      "54"
    ]
  },
  {
    "name": "၈၆ဂိတ်",
    "bus_ids": [
      "54"
    ]
  },
  {
    "name": "၈၉လမ်းဆုံ",
    "bus_ids": [
      "5"
    ]
  },
  {
    "name": "၉မိုင်",
    "bus_ids": [
      "6"
    ]
  }
]